gastepo/.DS_Store
gastepo/Cli.py
gastepo/Config/ApplicationConfig.yml
gastepo/Config/EnvironmentConfig.yml
gastepo/Core/.DS_Store
gastepo/Core/Base/BaseData.py
gastepo/Core/Base/CustomException.py
gastepo/Core/Base/__init__.py
gastepo/Core/Extend/AssertDependencyExtends.py
gastepo/Core/Extend/HamcrestCustomExtends.py
gastepo/Core/Extend/__init__.py
gastepo/Core/Server/ApiServer.py
gastepo/Core/Server/MainServer.py
gastepo/Core/Server/MockServer.py
gastepo/Core/Server/SlotServer.py
gastepo/Core/Server/__init__.py
gastepo/Core/Util/AllureUtils.py
gastepo/Core/Util/AssertionUtils.py
gastepo/Core/Util/CommonUtils.py
gastepo/Core/Util/ConfigUtils.py
gastepo/Core/Util/DataFrameUtils.py
gastepo/Core/Util/DatabaseUtils.py
gastepo/Core/Util/DingUtils.py
gastepo/Core/Util/ElkUtils.py
gastepo/Core/Util/EmailUtils.py
gastepo/Core/Util/EncryptUtils.py
gastepo/Core/Util/ExcelUtils.py
gastepo/Core/Util/JenkinsUtils.py
gastepo/Core/Util/LogUtils.py
gastepo/Core/Util/PostmanUtils.py
gastepo/Core/Util/RequestUtils.py
gastepo/Core/Util/SwaggerUtils.py
gastepo/Core/Util/TestCaseUtils.py
gastepo/Core/Util/ZipUtils.py
gastepo/Core/Util/__init__.py
gastepo/Core/__init__.py
gastepo/Output/.DS_Store
gastepo/Output/Coverage/.gitkeep
gastepo/Output/Log/.DS_Store
gastepo/Output/Log/.gitkeep
gastepo/Output/Log/GastepoAutoTest.log
gastepo/Output/Log/GastepoAutoTest.log.2021-09-08
gastepo/Output/Log/GastepoAutoTest.log.2021-10-19
gastepo/Output/Record/.gitkeep
gastepo/Output/Record/ApiRecordDocs.json
gastepo/QA/CommonUtilsTest.py
gastepo/QA/ConfigUtilsTest.py
gastepo/QA/__init__.py
gastepo/Resource/.DS_Store
gastepo/Resource/Allure/Allure.png
gastepo/Resource/Allure/categories.json
gastepo/Resource/Allure/environment.properties
gastepo/Resource/Ding/DingNotifyTemplate.json
gastepo/Resource/Others/file1.txt
gastepo/Resource/Others/file2.txt
gastepo/Run.py
gastepo/TestSuite/.DS_Store
gastepo/TestSuite/TestCase/.DS_Store
gastepo/TestSuite/TestCase/.gitkeep
gastepo-0.0.2.dist-info/entry_points.txt
gastepo-0.0.2.dist-info/WHEEL
gastepo-0.0.2.dist-info/METADATA
gastepo-0.0.2.dist-info/RECORD
