Metadata-Version: 2.1
Name: gastepo
Version: 0.0.2
Summary: An base-on Schema DSL automation framework of Restful API.
Home-page: https://github.com/bleiler1234/Gastepo
License: MIT
Keywords: schema,dsl,restful,api,test,pytest,allure,pandas,jsonpath,hamcrest
Author: yuzhonghua
Author-email: 583512498@qq.com
Requires-Python: >=3.7,<4.0
Classifier: Development Status :: 5 - Production/Stable
Classifier: License :: OSI Approved :: MIT License
Classifier: Operating System :: MacOS
Classifier: Operating System :: Microsoft :: Windows
Classifier: Operating System :: POSIX :: Linux
Classifier: Programming Language :: Python :: 3
Classifier: Programming Language :: Python :: 3.7
Classifier: Programming Language :: Python :: 3.8
Classifier: Programming Language :: Python :: 3.9
Classifier: Topic :: Software Development :: Quality Assurance
Classifier: Topic :: Software Development :: Testing
Requires-Dist: Flask (>=1.1.1,<2.0.0)
Requires-Dist: PyHamcrest (>=2.0.2,<3.0.0)
Requires-Dist: PyMySQL (>=0.9.3,<0.10.0)
Requires-Dist: PyYAML (>=5.3.1,<6.0.0)
Requires-Dist: SQLAlchemy (>=1.3.9,<2.0.0)
Requires-Dist: aiofiles (>=0.5.0,<0.6.0)
Requires-Dist: allure_pytest (>=2.8.6,<3.0.0)
Requires-Dist: allure_python_commons (>=2.8.6,<3.0.0)
Requires-Dist: colorlog (>=4.0.2,<5.0.0)
Requires-Dist: emoji (>=1.2.0,<2.0.0)
Requires-Dist: fastapi (>=0.58.1,<0.59.0)
Requires-Dist: jenkins (>=1.0.2,<2.0.0)
Requires-Dist: jsonpath (>=0.82,<0.83)
Requires-Dist: openpyxl (>=3.0.0,<4.0.0)
Requires-Dist: pandas (>=1.2.3,<2.0.0)
Requires-Dist: pycryptodome (>=3.9.7,<4.0.0)
Requires-Dist: pymongo (>=3.9.0,<4.0.0)
Requires-Dist: pytest (>=5.3.2,<6.0.0)
Requires-Dist: redis (>=3.5.3,<4.0.0)
Requires-Dist: requests (>=2.22.0,<3.0.0)
Requires-Dist: retrying (>=1.3.3,<2.0.0)
Requires-Dist: rsa (>=4.0,<5.0)
Requires-Dist: selenium (>=3.141.0,<4.0.0)
Requires-Dist: uvicorn (>=0.11.5,<0.12.0)
Requires-Dist: xlrd (>=1.2.0,<2.0.0)
Requires-Dist: xlutils (>=2.0.0,<3.0.0)
Requires-Dist: xlwt (>=1.3.0,<2.0.0)
Requires-Dist: xmltodict (>=0.12.0,<0.13.0)
Project-URL: Documentation, https://bleiler1234.github.io/Gastepo
Project-URL: Repository, https://github.com/bleiler1234/gastepo
